styletts2/Configs/config.yml
styletts2/Configs/config_ft.yml
styletts2/Configs/config_libritts.yml
styletts2/LICENSE
styletts2/Modules/__init__.py
styletts2/Modules/diffusion/__init__.py
styletts2/Modules/diffusion/diffusion.py
styletts2/Modules/diffusion/modules.py
styletts2/Modules/diffusion/sampler.py
styletts2/Modules/diffusion/utils.py
styletts2/Modules/discriminators.py
styletts2/Modules/hifigan.py
styletts2/Modules/istftnet.py
styletts2/Modules/slmadv.py
styletts2/Modules/utils.py
styletts2/Utils/ASR/__init__.py
styletts2/Utils/ASR/config.yml
styletts2/Utils/ASR/layers.py
styletts2/Utils/ASR/models.py
styletts2/Utils/JDC/__init__.py
styletts2/Utils/JDC/model.py
styletts2/Utils/PLBERT/config.yml
styletts2/Utils/PLBERT/util.py
styletts2/Utils/__init__.py
styletts2/__init__.py
styletts2/losses.py
styletts2/meldataset.py
styletts2/models.py
styletts2/optimizers.py
styletts2/phoneme.py
styletts2/requirements.txt
styletts2/text_utils.py
styletts2/tts.py
styletts2/utils.py
tts_webui_styletts2-0.1.11.dist-info/METADATA
tts_webui_styletts2-0.1.11.dist-info/WHEEL
tts_webui_styletts2-0.1.11.dist-info/licenses/LICENSE
tts_webui_styletts2-0.1.11.dist-info/RECORD
