Metadata-Version: 2.4
Name: tts-webui.styletts2
Version: 0.1.11
Summary: StyleTTS 2: Towards Human-Level Text-to-Speech through Style Diffusion and Adversarial Training with Large Speech Language Models. Original authors: Yinghao Aaron Li, Cong Han, Vinay S. Raghavan, Gavin Mischler, Nima Mesgarani. 
License: MIT
License-File: LICENSE
Author: Sidharth Rajaram
Author-email: rajaram@berkeley.edu
Requires-Python: >=3.9,<4.0
Classifier: License :: OSI Approved :: MIT License
Classifier: Programming Language :: Python :: 3
Classifier: Programming Language :: Python :: 3.9
Classifier: Programming Language :: Python :: 3.10
Classifier: Programming Language :: Python :: 3.11
Classifier: Programming Language :: Python :: 3.12
Classifier: Programming Language :: Python :: 3.13
Classifier: Programming Language :: Python :: 3.14
Requires-Dist: PyYAML (>=6.0.1,<7.0.0)
Requires-Dist: accelerate (>=0.25.0)
Requires-Dist: cached-path (>=1.6.0)
Requires-Dist: einops (>=0.7.0)
Requires-Dist: einops-exts (>=0.0.4)
Requires-Dist: filelock (>=3.12.4,<3.13)
Requires-Dist: gruut (>=2.3.4,<3.0.0)
Requires-Dist: gruut-ipa (>=0.13.0,<0.14.0)
Requires-Dist: gruut-lang-en (>=2.0.0,<3.0.0)
Requires-Dist: huggingface-hub (>=0.19.0)
Requires-Dist: librosa (>=0.9)
Requires-Dist: matplotlib (>=3.7.0)
Requires-Dist: munch (>=4.0.0,<5.0.0)
Requires-Dist: networkx (>=2.8.8,<3.0.0)
Requires-Dist: nltk (>=3.8.1,<4.0.0)
Requires-Dist: pydub (>=0.25.1,<0.26.0)
Requires-Dist: scipy (>=1.10.0)
Requires-Dist: soundfile (>=0.12.1,<0.13.0)
Requires-Dist: torch (>=2,<3)
Requires-Dist: torchaudio (>=2,<3)
Requires-Dist: tqdm (>=4.66.1)
Requires-Dist: transformers (>=4.36.0)
Requires-Dist: txtsplit (>=1.0.0,<2.0.0)
Requires-Dist: typing ; python_version < "3.5"
Requires-Dist: typing-extensions (>=4.9.0,<5.0.0)
Project-URL: Homepage, https://github.com/sidharthrajaram/StyleTTS2
Project-URL: Repository, https://github.com/sidharthrajaram/StyleTTS2
